[
  {
    "path": "/cssTest",
    "name": "cssTest",
    "meta": {"title": "样式动画", "icon": "system"},
    "component": "cssTest.vue"
  },
  {
    "path": "/canvasMain",
    "name": "canvas",
    "meta": {"title": "canvas", "icon": "system"},
    "component": "canvas/index.vue"
  },
  {
    "path": "/can_1",
    "name": "can_1",
    "meta": {"title": "can_1", "icon": "system"},
    "component": "canvas/can_1.vue"
  },
  {
    "path": "/can_2",
    "name": "can_2",
    "meta": {"title": "can_2", "icon": "system"},
    "component": "canvas/can_2.vue"
  },
  {
    "path": "/threeMain",
    "name": "three",
    "meta": {"title": "three", "icon": "system"},
    "component": "three/index.vue"
  },
  {
    "path": "/snake",
    "name": "snake",
    "meta": {"title": "snake", "icon": "system"},
    "component": "practice/snake.vue"
  },
  {
    "path": "/uploadTest",
    "name": "uploadTest",
    "meta": {"title": "upload", "icon": "system"},
    "component": "practice/uploadTest.vue"
  }
]